__init__.py
tsbs_rghosh8/__init__.py
tsbs_rghosh8/baseline.py
tsbs-0.0.2.dist-info/LICENSE
tsbs-0.0.2.dist-info/METADATA
tsbs-0.0.2.dist-info/WHEEL
tsbs-0.0.2.dist-info/top_level.txt
tsbs-0.0.2.dist-info/RECORD
