Metadata-Version: 2.1
Name: tsbs
Version: 0.0.2
Summary: Time Series Baseline
Author-email: Rajat Ghosh <rajat.ghosh11@gmail.com>
Classifier: Programming Language :: Python :: 3
Classifier: License :: OSI Approved :: MIT License
Classifier: Operating System :: OS Independent
Requires-Python: >=3.7
License-File: LICENSE
